simplellm/__init__.py
simplellm/dataloaders/__init__.py
simplellm/dataloaders/wikipedia_dataset.py
simplellm/gpt/__init__.py
simplellm/gpt/gpt3.py
simplellm/gpt/gpt_trainer.py
simplellm/gpt/gptbase.py
simplellm/llama/__init__.py
simplellm/llama/llama.py
simplellm/llama/llamabase.py
simplellm/tokenizers/__init__.py
simplellm/tokenizers/abstracttokenizer.py
simplellm/tokenizers/sptokenizer.py
simplellm-0.0.2.dist-info/LICENSE
simplellm-0.0.2.dist-info/METADATA
simplellm-0.0.2.dist-info/WHEEL
simplellm-0.0.2.dist-info/top_level.txt
simplellm-0.0.2.dist-info/RECORD
