Metadata-Version: 2.1
Name: simplellm
Version: 0.0.2
Summary: Build LLMs easily
Home-page: https://github.com/NikolayBlagoev/simplellm
Author: Nikolay Blagoev
Author-email: nickyblagoev@gmail.com
License: MIT License
Classifier: Programming Language :: Python :: 3
Classifier: License :: OSI Approved :: MIT License
Classifier: Operating System :: OS Independent
License-File: LICENSE
Requires-Dist: datasets
Requires-Dist: torch
Requires-Dist: sentencepiece
